sphinxcontrib_sadisplay-0.3.5.dev20210512-py3.9-nspkg.pth
sphinxcontrib/sadisp.py
sphinxcontrib_sadisplay-0.3.5.dev20210512.dist-info/METADATA
sphinxcontrib_sadisplay-0.3.5.dev20210512.dist-info/WHEEL
sphinxcontrib_sadisplay-0.3.5.dev20210512.dist-info/namespace_packages.txt
sphinxcontrib_sadisplay-0.3.5.dev20210512.dist-info/top_level.txt
sphinxcontrib_sadisplay-0.3.5.dev20210512.dist-info/RECORD
