Metadata-Version: 2.1
Name: sphinxcontrib-sadisplay
Version: 0.3.5.dev20210512
Summary: Sphinx "sadisplay" extension
Home-page: https://github.com/sphinx-contrib/sadisplay
Author: Evgeniy Tatarkin
Author-email: tatarkin.evg@gmail.com
License: BSD
Download-URL: http://pypi.python.org/pypi/sphinxcontrib-sadisplay
Platform: any
Classifier: Development Status :: 4 - Beta
Classifier: Environment :: Console
Classifier: Intended Audience :: Developers
Classifier: License :: OSI Approved :: BSD License
Classifier: Operating System :: OS Independent
Classifier: Programming Language :: Python
Classifier: Programming Language :: Python :: 2
Classifier: Programming Language :: Python :: 3
Classifier: Topic :: Documentation
Classifier: Topic :: Utilities
Requires-Dist: Sphinx (>=0.6)
Requires-Dist: sadisplay
